mcp_doris/__init__.py
mcp_doris/main.py
mcp_doris/mcp_env.py
mcp_doris/mcp_server.py
mseep_mcp_doris-0.1.5.dist-info/METADATA
mseep_mcp_doris-0.1.5.dist-info/WHEEL
mseep_mcp_doris-0.1.5.dist-info/entry_points.txt
mseep_mcp_doris-0.1.5.dist-info/licenses/LICENSE
mseep_mcp_doris-0.1.5.dist-info/RECORD
