Metadata-Version: 2.4
Name: mseep-mcp-doris
Version: 0.1.5
Summary: An MCP server for Apache Doris.
Project-URL: Home, https://github.com/morningman/mcp-doris
Author-email: mseep <support@skydeck.ai>
License-Expression: Apache-2.0
License-File: LICENSE
Requires-Python: >=3.13
Requires-Dist: mcp[cli]>=1.3.0
Requires-Dist: mysql-connector-python>=9.2.0
Requires-Dist: pip-system-certs>=4.0
Requires-Dist: python-dotenv>=1.0.1
Requires-Dist: uvicorn>=0.34.0
Provides-Extra: dev
Requires-Dist: pytest; extra == 'dev'
Requires-Dist: ruff; extra == 'dev'
